xml4h/__init__.py
xml4h/builder.py
xml4h/exceptions.py
xml4h/nodes.py
xml4h/writer.py
xml4h/impls/__init__.py
xml4h/impls/interface.py
xml4h/impls/lxml_etree.py
xml4h/impls/xml_dom_minidom.py
xml4h/impls/xml_etree_elementtree.py
xml4h-1.0.dist-info/LICENSE
xml4h-1.0.dist-info/METADATA
xml4h-1.0.dist-info/WHEEL
xml4h-1.0.dist-info/top_level.txt
xml4h-1.0.dist-info/RECORD
